unfrs-0.1.1.dist-info/METADATA
unfrs-0.1.1.dist-info/WHEEL
unf_rs/__init__.py
unf_rs/unf_rs.cpython-37m-x86_64-linux-gnu.so
unfrs-0.1.1.dist-info/RECORD
